tossicat_python-0.1.3.dist-info/METADATA
tossicat_python-0.1.3.dist-info/WHEEL
tossicat_python-0.1.3.dist-info/licenses/LICENSE
tossicat/__init__.py
tossicat/__init__.pyi
tossicat/py.typed
tossicat/tossicat.pyd
tossicat_python-0.1.3.dist-info/RECORD
